smartoscreid/__init__.py
smartoscreid/config.py
smartoscreid/load_video.py
smartoscreid/people_counting.py
smartoscreid/reid.py
smartoscreid/utils.py
smartoscreid/torchreid/__init__.py
smartoscreid/torchreid/data/__init__.py
smartoscreid/torchreid/data/datamanager.py
smartoscreid/torchreid/data/sampler.py
smartoscreid/torchreid/data/transforms.py
smartoscreid/torchreid/data/datasets/__init__.py
smartoscreid/torchreid/data/datasets/dataset.py
smartoscreid/torchreid/data/datasets/image/__init__.py
smartoscreid/torchreid/data/datasets/image/cuhk01.py
smartoscreid/torchreid/data/datasets/image/cuhk02.py
smartoscreid/torchreid/data/datasets/image/cuhk03.py
smartoscreid/torchreid/data/datasets/image/dukemtmcreid.py
smartoscreid/torchreid/data/datasets/image/grid.py
smartoscreid/torchreid/data/datasets/image/ilids.py
smartoscreid/torchreid/data/datasets/image/market1501.py
smartoscreid/torchreid/data/datasets/image/msmt17.py
smartoscreid/torchreid/data/datasets/image/prid.py
smartoscreid/torchreid/data/datasets/image/sensereid.py
smartoscreid/torchreid/data/datasets/image/viper.py
smartoscreid/torchreid/data/datasets/video/__init__.py
smartoscreid/torchreid/data/datasets/video/dukemtmcvidreid.py
smartoscreid/torchreid/data/datasets/video/ilidsvid.py
smartoscreid/torchreid/data/datasets/video/mars.py
smartoscreid/torchreid/data/datasets/video/prid2011.py
smartoscreid/torchreid/engine/__init__.py
smartoscreid/torchreid/engine/engine.py
smartoscreid/torchreid/engine/image/__init__.py
smartoscreid/torchreid/engine/image/softmax.py
smartoscreid/torchreid/engine/image/triplet.py
smartoscreid/torchreid/engine/video/__init__.py
smartoscreid/torchreid/engine/video/softmax.py
smartoscreid/torchreid/engine/video/triplet.py
smartoscreid/torchreid/losses/__init__.py
smartoscreid/torchreid/losses/cross_entropy_loss.py
smartoscreid/torchreid/losses/hard_mine_triplet_loss.py
smartoscreid/torchreid/metrics/__init__.py
smartoscreid/torchreid/metrics/accuracy.py
smartoscreid-0.0.2.dist-info/LICENSE
smartoscreid-0.0.2.dist-info/METADATA
smartoscreid-0.0.2.dist-info/WHEEL
smartoscreid-0.0.2.dist-info/top_level.txt
smartoscreid-0.0.2.dist-info/RECORD
