Metadata-Version: 2.1
Name: smartoscreid
Version: 0.0.2
Summary: People counting project
Home-page: https://git02.smartosc.com/division-1/computer-vision-project/people_counting
Author: CLOUD Team
License: MIT
Keywords: Person Re-Identification,Deep Learning,Computer Vision
License-File: LICENSE
Requires-Dist: ultralytics==8.2.74
Requires-Dist: lapx>=0.5.2
Requires-Dist: gdown==5.2.0
Requires-Dist: torch==2.4.0
Requires-Dist: torchvision==0.19.0
Requires-Dist: tqdm==4.66.5
Requires-Dist: pandas==2.2.2
Requires-Dist: numpy==1.26.4
Requires-Dist: Cython
Requires-Dist: opencv-python==4.10.0.84
Requires-Dist: scikit-learn==1.5.1
Requires-Dist: scipy==1.14.0
Requires-Dist: tensorboard==2.17.0
